weather.py
sseserver-0.1.0.dist-info/METADATA
sseserver-0.1.0.dist-info/WHEEL
sseserver-0.1.0.dist-info/top_level.txt
sseserver-0.1.0.dist-info/RECORD
