Metadata-Version: 2.4
Name: sseserver
Version: 0.1.0
Summary: Add your description here
Requires-Python: >=3.10
Requires-Dist: httpx>=0.28.1
Requires-Dist: mcp>=1.13.0
